nndict/__init__.py
nndict/never_none_dict.py
nndict-2.0.1.dist-info/LICENSE
nndict-2.0.1.dist-info/WHEEL
nndict-2.0.1.dist-info/METADATA
nndict-2.0.1.dist-info/RECORD
